nodeology/.DS_Store
nodeology/__init__.py
nodeology/client.py
nodeology/interface.py
nodeology/log.py
nodeology/node.py
nodeology/state.py
nodeology/workflow.py
nodeology/__pycache__/__init__.cpython-311.pyc
nodeology/__pycache__/client.cpython-311.pyc
nodeology/__pycache__/interface.cpython-311.pyc
nodeology/__pycache__/log.cpython-311.pyc
nodeology/__pycache__/node.cpython-311.pyc
nodeology/__pycache__/state.cpython-311.pyc
nodeology/__pycache__/ui.cpython-311.pyc
nodeology/__pycache__/ui_server.cpython-311.pyc
nodeology/__pycache__/workflow.cpython-311.pyc
nodeology-0.0.3.dist-info/licenses/LICENSE
nodeology-0.0.3.dist-info/METADATA
nodeology-0.0.3.dist-info/WHEEL
nodeology-0.0.3.dist-info/top_level.txt
nodeology-0.0.3.dist-info/RECORD
