Metadata-Version: 2.4
Name: nodeology
Version: 0.0.3
Summary: Foundation AI-Enhanced Scientific Workflow
Home-page: https://github.com/xyin-anl/nodeology
Author: Xiangyu Yin
Author-email: xyin@anl.gov
Classifier: Intended Audience :: Science/Research
Classifier: Programming Language :: Python :: 3
Requires-Python: >=3.10
License-File: LICENSE
Requires-Dist: requests
Requires-Dist: pyyaml
Requires-Dist: typing-extensions
Requires-Dist: numpy
Requires-Dist: plotly
Requires-Dist: kaleido
Requires-Dist: langgraph<=0.2.45
Requires-Dist: litellm>=1.0.0
Requires-Dist: langfuse>=2.0.0
Requires-Dist: chainlit>=2.0.0
Dynamic: author
Dynamic: author-email
Dynamic: classifier
Dynamic: description
Dynamic: description-content-type
Dynamic: home-page
Dynamic: license-file
Dynamic: requires-dist
Dynamic: requires-python
Dynamic: summary
